watercrawl_plugin/__init__.py
watercrawl_plugin/base.py
watercrawl_plugin/utils.py
watercrawl_plugin-0.1.0.dist-info/LICENSE
watercrawl_plugin-0.1.0.dist-info/METADATA
watercrawl_plugin-0.1.0.dist-info/WHEEL
watercrawl_plugin-0.1.0.dist-info/top_level.txt
watercrawl_plugin-0.1.0.dist-info/RECORD
