Metadata-Version: 2.1
Name: watercrawl-plugin
Version: 0.1.0
Summary: This project used for writing WaterCrawl plugins
Author-email: AmirMohsen Asaran <info@watercrawl.ai>
Project-URL: Homepage, https://github.com/watercrawl/watercrawl-plugin
Project-URL: Issues, https://github.com/watercrawl/watercrawl/issues
Classifier: Programming Language :: Python :: 3
Classifier: License :: OSI Approved :: MIT License
Classifier: Operating System :: OS Independent
Requires-Python: >=3.11
License-File: LICENSE
Requires-Dist: jsonschema==4.23.0
